{
  "timestamp": "20251030_123809",
  "conversion_results": {
    "float32": {
      "file_path": "models/tflite_optimized/hybrid_cnn_gru_optimized_float32.tflite",
      "size_mb": 4.300270080566406,
      "status": "success"
    },
    "float16": {
      "file_path": "models/tflite_optimized/hybrid_cnn_gru_optimized_float16.tflite",
      "size_mb": 2.16162109375,
      "status": "success"
    },
    "dynamic": {
      "file_path": "models/tflite_optimized/hybrid_cnn_gru_optimized_dynamic.tflite",
      "size_mb": 1.0902938842773438,
      "status": "success"
    }
  },
  "test_results": [
    {
      "model_name": "Hybrid CNN-GRU (FLOAT32)",
      "model_path": "models/tflite_optimized/hybrid_cnn_gru_optimized_float32.tflite",
      "model_size_mb": 4.300270080566406,
      "avg_inference_time_ms": 2.6888608932495117,
      "input_shape": [
        1,
        256
      ],
      "output_shape": [
        1,
        1
      ],
      "status": "success"
    },
    {
      "model_name": "Hybrid CNN-GRU (FLOAT16)",
      "model_path": "models/tflite_optimized/hybrid_cnn_gru_optimized_float16.tflite",
      "model_size_mb": 2.16162109375,
      "avg_inference_time_ms": 2.656269073486328,
      "input_shape": [
        1,
        256
      ],
      "output_shape": [
        1,
        1
      ],
      "status": "success"
    },
    {
      "model_name": "Hybrid CNN-GRU (DYNAMIC)",
      "model_path": "models/tflite_optimized/hybrid_cnn_gru_optimized_dynamic.tflite",
      "model_size_mb": 1.0902938842773438,
      "avg_inference_time_ms": 3.4847497940063477,
      "input_shape": [
        1,
        256
      ],
      "output_shape": [
        1,
        1
      ],
      "status": "success"
    }
  ]
}